auralislib/__version__.py
auralislib/STT/inference.py
auralislib/TTS/synth.py
auralislib/VC/clone.py
auralislib/audio/preprocessing.py
auralislib/models/ctc_model.py
auralislib/models/tacotron_stub.py
auralislib/models/voice_clone_decoder.py
auralislib/utils/audio_utils.py
auralislib/utils/image_utils.py
auralislib/utils/model_utils.py
auralislib-1.0.2.dist-info/licenses/LICENSE
auralislib-1.0.2.dist-info/METADATA
auralislib-1.0.2.dist-info/WHEEL
auralislib-1.0.2.dist-info/top_level.txt
auralislib-1.0.2.dist-info/RECORD
