Metadata-Version: 2.4
Name: auralislib
Version: 1.0.2
Summary: Intelligent Python Library for Voice Cloning, Audio Synthesis, and Image Generation
Author-email: Rugved Joshi <rugvedsamruddhi@gmail.com>
License: MIT License
Project-URL: Homepage, https://github.com/joshirugved11/auralis
Project-URL: Repository, https://github.com/joshirugved11/auralis
Project-URL: Bug Tracker, https://github.com/joshirugved11/auralis/issues
Keywords: voice cloning,audio synthesis,tts,gan,image generation,python library
Requires-Python: >=3.8
License-File: LICENSE
Requires-Dist: numpy>=1.23
Requires-Dist: soundfile>=0.12
Requires-Dist: scipy>=1.10
Requires-Dist: requests>=2.31
Requires-Dist: Pillow>=9.4
Requires-Dist: pyttsx3>=2.90
Requires-Dist: tqdm>=4.66
Requires-Dist: python-dotenv>=1.0
Requires-Dist: click>=8.1
Requires-Dist: torch>=2.0
Requires-Dist: torchaudio>=2.0
Requires-Dist: opencv-python>=4.8
Requires-Dist: transformers>=4.30
Requires-Dist: diffusers>=0.20
Requires-Dist: librosa>=0.10
Requires-Dist: pydub>=0.25
Requires-Dist: scikit-learn>=1.2
Requires-Dist: matplotlib>=3.7
Dynamic: license-file
